autolike/__init__.py
autolike-1.0.4.dist-info/METADATA
autolike-1.0.4.dist-info/WHEEL
autolike-1.0.4.dist-info/top_level.txt
autolike-1.0.4.dist-info/RECORD
