Metadata-Version: 2.1
Name: autolike
Version: 1.0.4
Summary: Automatically like any given Facebook URL if the user is logged in.
Home-page: http://github.com/arsho/autolike
Author: Ahmedur Rahman Shovon
Author-email: shovon.sylhet@gmail.com
License: BSD
Keywords: Facebook fb like liker autolike autoliker automation
Classifier: License :: OSI Approved :: BSD License
Classifier: Operating System :: OS Independent
Classifier: Programming Language :: Python :: 3
Classifier: Intended Audience :: Developers
Classifier: Development Status :: 5 - Production/Stable
Classifier: Topic :: Software Development :: Libraries :: Python Modules
Requires-Dist: pymsgbox
Requires-Dist: PyTweening >=1.0.1
Requires-Dist: Pillow
Requires-Dist: pyscreeze
Requires-Dist: pyautogui
